memoize.py
setup.cfg
setup.py
memoize_2.egg-info/PKG-INFO
memoize_2.egg-info/SOURCES.txt
memoize_2.egg-info/dependency_links.txt
memoize_2.egg-info/top_level.txt