Metadata-Version: 1.0
Name: memoize-2
Version: 0.1.0
Summary: UNKNOWN
Home-page: UNKNOWN
Author: Rodney Gomes
Author-email: rodneygomes@gmail.com
License: Apache 2.0 License
Keywords: memoize,library
Platform: UNKNOWN
